{
  "slug": "ch12-thermodynamics",
  "title": "Thermodynamics",
  "icon": "🔥",
  "description": "Thermodynamic processes, first and second laws, heat engines, refrigerators, and the Carnot theorem.",
  "lessons": [
    {
      "slug": "carnot-theorem",
      "title": "Carnot Theorem",
      "order": 1
    },
    {
      "slug": "first-law",
      "title": "Zeroth & First Law of Thermodynamics",
      "order": 2
    },
    {
      "slug": "heat-engines",
      "title": "Heat Engines & Refrigerators",
      "order": 3
    },
    {
      "slug": "second-law",
      "title": "Second Law & Entropy",
      "order": 4
    },
    {
      "slug": "thermodynamic-processes",
      "title": "Thermodynamic Processes",
      "order": 5
    }
  ]
}